{"companyOfficers": [], "executiveTeam": [], "maxAge": 86400, "priceHint": 2, "previousClose": 8.7, "open": 9.0, "dayLow": 8.2147, "dayHigh": 8.2147, "regularMarketPreviousClose": 8.7, "regularMarketOpen": 9.0, "regularMarketDayLow": 8.2147, "regularMarketDayHigh": 8.2147, "volume": 0, "regularMarketVolume": 0, "averageVolume": 0, "averageVolume10days": 0, "averageDailyVolume10Day": 0, "bid": 0.0, "ask": 0.0, "bidSize": 8, "askSize": 8, "totalAssets": 671518, "fiftyTwoWeekLow": 8.2147, "fiftyTwoWeekHigh": 9.0, "fiftyDayAverage": 9.0, "twoHundredDayAverage": 9.0, "currency": "USD", "tradeable": false, "ytdReturn": 0.0, "beta3Year": 0.59, "fundFamily": "Deutsche Bank AG", "fundInceptionDate": 1208131200, "legalType": "Exchange Traded Fund", "threeYearAverageReturn": 0.0, "fiveYearAverageReturn": -0.0320135, "quoteType": "ETF", "symbol": "AGF", "language": "en-US", "region": "US", "typeDisp": "ETF", "quoteSourceName": "Delayed Quote", "triggerable": true, "customPriceAlertConfidence": "HIGH", "marketState": "PREPRE", "regularMarketChangePercent": 0.0, "regularMarketPrice": 9.0, "shortName": "DB Agriculture Long ETN due Apr", "longName": "DB Agriculture Long ETN", "corporateActions": [], "regularMarketTime": 1554903395, "exchange": "PCX", "messageBoardId": "finmb_43533060", "exchangeTimezoneName": "America/New_York", "exchangeTimezoneShortName": "EDT", "gmtOffSetMilliseconds": -14400000, "market": "us_market", "esgPopulated": false, "hasPrePostMarketData": true, "firstTradeDateMilliseconds": 1230820200000, "regularMarketChange": 0.0, "regularMarketDayRange": "8.2147 - 8.2147", "fullExchangeName": "NYSEArca", "averageDailyVolume3Month": 0, "fiftyTwoWeekLowChange": 0.78530025, "fiftyTwoWeekLowChangePercent": 0.095596954, "fiftyTwoWeekRange": "8.2147 - 9.0", "fiftyTwoWeekHighChange": 0.0, "fiftyTwoWeekHighChangePercent": 0.0, "fiftyTwoWeekChangePercent": 0.0, "trailingThreeMonthReturns": 0.0, "trailingThreeMonthNavReturns": 0.0, "netAssets": 671518.0, "fiftyDayAverageChange": 0.0, "fiftyDayAverageChangePercent": 0.0, "twoHundredDayAverageChange": 0.0, "twoHundredDayAverageChangePercent": 0.0, "netExpenseRatio": 0.75, "sourceInterval": 15, "exchangeDataDelayedBy": 0, "cryptoTradeable": false, "trailingPegRatio": null}